setup.cfg
setup.py
execmode/__init__.py
execmode/instance.py
execmode/logging.py
execmode/state.py
execmode.egg-info/PKG-INFO
execmode.egg-info/SOURCES.txt
execmode.egg-info/dependency_links.txt
execmode.egg-info/top_level.txt