Metadata-Version: 1.0
Name: execmode
Version: 1.1
Summary: verbose debug, succint release mode behaviors
Home-page: https://github.com/mlabbe/execmode
Author: Michael Labbe
Author-email: mike@frogtoss.com
License: UNKNOWN
Keywords: logging,debug,release
Platform: UNKNOWN
